LICENSE.txt
setup.cfg
setup.py
tensorrt_dispatch/__init__.py
tensorrt_dispatch_cu11.egg-info/PKG-INFO
tensorrt_dispatch_cu11.egg-info/SOURCES.txt
tensorrt_dispatch_cu11.egg-info/dependency_links.txt
tensorrt_dispatch_cu11.egg-info/requires.txt
tensorrt_dispatch_cu11.egg-info/top_level.txt
tensorrt_dispatch_cu11.egg-info/zip-safe